setup.py
client/__init__.py
client/add_contact.py
client/client_oop.py
client/common_oop.py
client/database.py
client/decos.py
client/del_contact.py
client/descriptors.py
client/errors.py
client/main_window.py
client/main_window_conv.py
client/metaclasses.py
client/start_dialog.py
client/transport.py
client/log/__init__.py
client/log/config/__init__.py
client/log/config/client_log_config.py
client/log/config/server_log_config.py
client/unit_tests/__init__.py
client/unit_tests/test_client.py
client/unit_tests/test_common.py
client/unit_tests/test_server.py
message_client_tchka.egg-info/PKG-INFO
message_client_tchka.egg-info/SOURCES.txt
message_client_tchka.egg-info/dependency_links.txt
message_client_tchka.egg-info/requires.txt
message_client_tchka.egg-info/top_level.txt