Metadata-Version: 1.0
Name: message-client-tchka
Version: 1.0.0
Summary: OneMore Message Client
Home-page: UNKNOWN
Author: Elena Nikolaeva
Author-email: tchka777@gmail.com
License: UNKNOWN
Platform: UNKNOWN
